nepal_gateways/CHANGELOG.md
nepal_gateways/__init__.py
nepal_gateways/factory.py
nepal_gateways/utils.py
nepal_gateways/core/__init__.py
nepal_gateways/core/base.py
nepal_gateways/core/exceptions.py
nepal_gateways/esewa/__init__.py
nepal_gateways/esewa/client.py
nepal_gateways/esewa/config.py
nepal_gateways/khalti/__init__.py
nepal_gateways/khalti/client.py
nepal_gateways/khalti/config.py
nepal_gateways-0.2.0.dist-info/METADATA
nepal_gateways-0.2.0.dist-info/WHEEL
nepal_gateways-0.2.0.dist-info/licenses/LICENSE
nepal_gateways-0.2.0.dist-info/RECORD
