Metadata-Version: 2.4
Name: nepal-gateways
Version: 0.2.0
Summary: A Python library for easy integration with Nepali payment gateways like eSewa and Khalti.
Project-URL: Homepage, https://github.com/polymorphisma/nepal-gateways
Project-URL: Documentation, https://github.com/polymorphisma/nepal-gateways/blob/main/README.md
Project-URL: Repository, https://github.com/polymorphisma/nepal-gateways
Project-URL: Bug Tracker, https://github.com/polymorphisma/nepal-gateways/issues
Author-email: polymorphisma <shrawansunar.6@gmail.com>
License: MIT License
License-File: LICENSE
Keywords: digital wallet,esewa,fintech,gateway,nepal,nepali payments,payment,python
Classifier: Development Status :: 3 - Alpha
Classifier: Intended Audience :: Developers
Classifier: License :: OSI Approved :: MIT License
Classifier: Natural Language :: English
Classifier: Operating System :: OS Independent
Classifier: Programming Language :: Python :: 3
Classifier: Programming Language :: Python :: 3.10
Classifier: Programming Language :: Python :: 3.11
Classifier: Programming Language :: Python :: 3.12
Classifier: Topic :: Office/Business :: Financial
Classifier: Topic :: Software Development :: Libraries :: Python Modules
Classifier: Typing :: Typed
Requires-Python: >=3.10
Requires-Dist: requests>=2.20.0
Provides-Extra: dev
Requires-Dist: black; extra == 'dev'
Requires-Dist: build; extra == 'dev'
Requires-Dist: flask>=3.0.0; extra == 'dev'
Requires-Dist: pytest-mock>=3.12.0; extra == 'dev'
Requires-Dist: pytest>=8.0.0; extra == 'dev'
Requires-Dist: requests-mock>=1.11.0; extra == 'dev'
Requires-Dist: ruff; extra == 'dev'
Requires-Dist: twine; extra == 'dev'
